lerobot_dashboard/__init__.py
lerobot_dashboard/main.py
lerobot_dashboard-0.4.1.dist-info/METADATA
lerobot_dashboard-0.4.1.dist-info/WHEEL
lerobot_dashboard-0.4.1.dist-info/entry_points.txt
lerobot_dashboard-0.4.1.dist-info/RECORD
