Metadata-Version: 2.4
Name: lerobot-dashboard
Version: 0.4.1
Summary: Dora Node Dashboard for LeRobot dataset recording.
License: MIT
Author: Hennzau
Author-email: <dev@enzo-le-van.fr>
Requires-Python: >=3.9
Classifier: License :: OSI Approved :: MIT License
Classifier: Programming Language :: Python :: 3
Classifier: Programming Language :: Python :: 3.9
Classifier: Programming Language :: Python :: 3.10
Classifier: Programming Language :: Python :: 3.11
Classifier: Programming Language :: Python :: 3.12
Classifier: Programming Language :: Python :: 3.13
Classifier: Programming Language :: Python :: 3.14
Requires-Dist: dora-rs (==0.3.5)
Requires-Dist: numpy (<=2.0.0)
Requires-Dist: opencv-python (>=4.1.1)
Requires-Dist: pygame (>=2.6.0,<2.7.0)
